{
  "face1.png": {
    tipo: "face",
  },
  "face2.png": {
    tipo: "face",
  },
  "face3.png": {
    tipo: "face",
  },
  "face4.png": {
    tipo: "face",
  },
  "blackMan1.png": {
    tipo: "hair",
  },
  "blackMan2.png": {
    tipo: "hair",
  },
  "blackMan3.png": {
    tipo: "hair",
  },
  "blackMan4.png": {
    tipo: "hair",
  },
  "blackMan5.png": {
    tipo: "hair",
  },
  "blackMan6.png": {
    tipo: "hair",
  },
  "blackMan7.png": {
    tipo: "hair",
  },
  "blackMan8.png": {
    tipo: "hair",
  },
  "blondeMan1.png": {
    tipo: "hair",
  },
  "blondeMan2.png": {
    tipo: "hair",
  },
  "blondeMan3.png": {
    tipo: "hair",
  },
  "blondeMan4.png": {
    tipo: "hair",
  },
  "blondeMan5.png": {
    tipo: "hair",
  },
  "blondeMan6.png": {
    tipo: "hair",
  },
  "blondeMan7.png": {
    tipo: "hair",
  },
  "blondeMan8.png": {
    tipo: "hair",
  },
  "brown1Man1.png": {
    tipo: "hair",
  },
  "brown1Man2.png": {
    tipo: "hair",
  },
  "brown1Man3.png": {
    tipo: "hair",
  },
  "brown1Man4.png": {
    tipo: "hair",
  },
  "brown1Man5.png": {
    tipo: "hair",
  },
  "brown1Man6.png": {
    tipo: "hair",
  },
  "brown1Man7.png": {
    tipo: "hair",
  },
  "brown1Man8.png": {
    tipo: "hair",
  },
  "brown2Man1.png": {
    tipo: "hair",
  },
  "brown2Man2.png": {
    tipo: "hair",
  },
  "brown2Man3.png": {
    tipo: "hair",
  },
  "brown2Man4.png": {
    tipo: "hair",
  },
  "brown2Man5.png": {
    tipo: "hair",
  },
  "brown2Man6.png": {
    tipo: "hair",
  },
  "brown2Man7.png": {
    tipo: "hair",
  },
  "brown2Man8.png": {
    tipo: "hair",
  },
  "greyMan1.png": {
    tipo: "hair",
  },
  "greyMan2.png": {
    tipo: "hair",
  },
  "greyMan3.png": {
    tipo: "hair",
  },
  "greyMan4.png": {
    tipo: "hair",
  },
  "greyMan5.png": {
    tipo: "hair",
  },
  "greyMan6.png": {
    tipo: "hair",
  },
  "greyMan7.png": {
    tipo: "hair",
  },
  "greyMan8.png": {
    tipo: "hair",
  },
  "redMan1.png": {
    tipo: "hair",
  },
  "pantsBrown1.png": {
    tipo: "hair",
  },
  "redMan2.png": {
    tipo: "hair",
  },
  "redMan3.png": {
    tipo: "hair",
  },
  "redMan4.png": {
    tipo: "hair",
  },
  "redMan5.png": {
    tipo: "hair",
  },
  "redMan6.png": {
    tipo: "hair",
  },
  "redMan7.png": {
    tipo: "hair",
  },
  "redMan8.png": {
    tipo: "hair",
  },
  "tanMan1.png": {
    tipo: "hair",
  },
  "tanMan2.png": {
    tipo: "hair",
  },
  "tanMan3.png": {
    tipo: "hair",
  },
  "tanMan4.png": {
    tipo: "hair",
  },
  "tanMan5.png": {
    tipo: "hair",
  },
  "tanMan6.png": {
    tipo: "hair",
  },
  "tanMan7.png": {
    tipo: "hair",
  },
  "tanMan8.png": {
    tipo: "hair",
  },
  "whiteMan1.png": {
    tipo: "hair",
  },
  "whiteMan2.png": {
    tipo: "hair",
  },
  "whiteMan3.png": {
    tipo: "hair",
  },
  "whiteMan4.png": {
    tipo: "hair",
  },
  "whiteMan5.png": {
    tipo: "hair",
  },
  "whiteMan6.png": {
    tipo: "hair",
  },
  "whiteMan7.png": {
    tipo: "hair",
  },
  "whiteMan8.png": {
    tipo: "hair",
  },
  
  "pantsBlue1_long.png": {
    tipo: "pants",
  },

  "pantsBlue2_long.png": {
    tipo: "pants",
  },
  "pantsBrown_long.png": {
    tipo: "pants",
  },
  "pantsGreen_long.png": {
    tipo: "pants",
  },
  "pantsGrey_long.png": {
    tipo: "pants",
  },
  "pantsLightBlue_long.png": {
    tipo: "pants",
  },
  "pantsNavy_long.png": {
    tipo: "pants",
  },

  
  "pantsPine_long.png": {
    tipo: "pants",
  },

  "pantsRed_long.png": {
    tipo: "pants",
  },

  "pantsTan_long.png": {
    tipo: "pants",
  },

  "pantsWhite_long.png": {
    tipo: "pants",
  },

  "legYellow_long.png": {
    tipo: "pants",
  },
  "blueArm_long.png": {
    tipo: "arm",
  },

  "blueShirt1.png": {
    tipo: "shirt",
  },
  "blueShirt2.png": {
    tipo: "shirt",
  },
  "blueShirt3.png": {
    tipo: "shirt",
  },
  "blueShirt4.png": {
    tipo: "shirt",
  },
  "blueShirt5.png": {
    tipo: "shirt",
  },
  "blueShirt6.png": {
    tipo: "shirt",
  },
  "blueShirt7.png": {
    tipo: "shirt",
  },
  "blueShirt8.png": {
    tipo: "shirt",
  },
  "greenArm_long.png": {
    tipo: "arm",
  },

  "greenShirt1.png": {
    tipo: "shirt",
  },
  "greenShirt2.png": {
    tipo: "shirt",
  },
  "greenShirt3.png": {
    tipo: "shirt",
  },
  "greenShirt4.png": {
    tipo: "shirt",
  },
  "greenShirt5.png": {
    tipo: "shirt",
  },
  "greenShirt6.png": {
    tipo: "shirt",
  },
  "greenShirt7.png": {
    tipo: "shirt",
  },
  "greenShirt8.png": {
    tipo: "shirt",
  },
  "greyArm_long.png": {
    tipo: "arm",
  },

  "greyShirt1.png": {
    tipo: "shirt",
  },
  "greyShirt2.png": {
    tipo: "shirt",
  },
  "greyShirt3.png": {
    tipo: "shirt",
  },
  "greyShirt4.png": {
    tipo: "shirt",
  },
  "greyShirt5.png": {
    tipo: "shirt",
  },
  "greyShirt6.png": {
    tipo: "shirt",
  },
  "greyShirt7.png": {
    tipo: "shirt",
  },
  "greyShirt8.png": {
    tipo: "shirt",
  },
  "navyArm_long.png": {
    tipo: "arm",
  },

  "navyShirt1.png": {
    tipo: "shirt",
  },
  "navyShirt2.png": {
    tipo: "shirt",
  },
  "navyShirt3.png": {
    tipo: "shirt",
  },
  "navyShirt4.png": {
    tipo: "shirt",
  },
  "navyShirt5.png": {
    tipo: "shirt",
  },
  "navyShirt6.png": {
    tipo: "shirt",
  },
  "navyShirt7.png": {
    tipo: "shirt",
  },
  "navyShirt8.png": {
    tipo: "shirt",
  },
  "pineArm_long.png": {
    tipo: "arm",
  },

  "pineShirt1.png": {
    tipo: "shirt",
  },
  "pineShirt2.png": {
    tipo: "shirt",
  },
  "pineShirt3.png": {
    tipo: "shirt",
  },
  "pineShirt4.png": {
    tipo: "shirt",
  },
  "pineShirt5.png": {
    tipo: "shirt",
  },
  "pineShirt6.png": {
    tipo: "shirt",
  },
  "pineShirt7.png": {
    tipo: "shirt",
  },
  "pineShirt8.png": {
    tipo: "shirt",
  },
  "redArm_long.png": {
    tipo: "arm",
  },

  "redShirt1.png": {
    tipo: "shirt",
  },
  "redShirt2.png": {
    tipo: "shirt",
  },
  "redShirt3.png": {
    tipo: "shirt",
  },
  "redShirt4.png": {
    tipo: "shirt",
  },
  "redShirt5.png": {
    tipo: "shirt",
  },
  "redShirt6.png": {
    tipo: "shirt",
  },
  "redShirt7.png": {
    tipo: "shirt",
  },
  "redShirt8.png": {
    tipo: "shirt",
  },
  "armWhite_long.png": {
    tipo: "arm",
  },

  "whiteShirt1.png": {
    tipo: "shirt",
  },
  "whiteShirt2.png": {
    tipo: "shirt",
  },
  "whiteShirt3.png": {
    tipo: "shirt",
  },
  "whiteShirt4.png": {
    tipo: "shirt",
  },
  "whiteShirt5.png": {
    tipo: "shirt",
  },
  "whiteShirt6.png": {
    tipo: "shirt",
  },
  "whiteShirt7.png": {
    tipo: "shirt",
  },
  "whiteShirt8.png": {
    tipo: "shirt",
  },
  "armYellow_long.png": {
    tipo: "arm",
  },
  "shirtYellow1.png": {
    tipo: "shirt",
  },
  "shirtYellow2.png": {
    tipo: "shirt",
  },
  "shirtYellow3.png": {
    tipo: "shirt",
  },
  "shirtYellow4.png": {
    tipo: "shirt",
  },
  "shirtYellow5.png": {
    tipo: "shirt",
  },
  "shirtYellow6.png": {
    tipo: "shirt",
  },
  "shirtYellow7.png": {
    tipo: "shirt",
  },
  "shirtYellow8.png": {
    tipo: "shirt",
  },
  "blackShoe1.png": {
    tipo: "shoe",
  },
  "blackShoe2.png": {
    tipo: "shoe",
  },
  "blackShoe3.png": {
    tipo: "shoe",
  },
  "blackShoe4.png": {
    tipo: "shoe",
  },
  "blackShoe5.png": {
    tipo: "shoe",
  },
  "blueShoe1.png": {
    tipo: "shoe",
  },
  "blueShoe2.png": {
    tipo: "shoe",
  },
  "blueShoe3.png": {
    tipo: "shoe",
  },
  "blueShoe4.png": {
    tipo: "shoe",
  },
  "blueShoe5.png": {
    tipo: "shoe",
  },
  "brownShoe1.png": {
    tipo: "shoe",
  },
  "brownShoe2.png": {
    tipo: "shoe",
  },
  "brownShoe3.png": {
    tipo: "shoe",
  },
  "brownShoe4.png": {
    tipo: "shoe",
  },
  "brownShoe5.png": {
    tipo: "shoe",
  },
  "brown2Shoe1.png": {
    tipo: "shoe",
  },
  "brown2Shoe2.png": {
    tipo: "shoe",
  },
  "brown2Shoe3.png": {
    tipo: "shoe",
  },
  "brown2Shoe4.png": {
    tipo: "shoe",
  },
  "brown2Shoe5.png": {
    tipo: "shoe",
  },
  "greyShoe1.png": {
    tipo: "shoe",
  },
  "greyShoe2.png": {
    tipo: "shoe",
  },
  "greyShoe3.png": {
    tipo: "shoe",
  },
  "greyShoe4.png": {
    tipo: "shoe",
  },
  "greyShoe5.png": {
    tipo: "shoe",
  },
  "redShoe1.png": {
    tipo: "shoe",
  },
  "redShoe2.png": {
    tipo: "shoe",
  },
  "redShoe3.png": {
    tipo: "shoe",
  },
  "redShoe4.png": {
    tipo: "shoe",
  },
  "redShoe5.png": {
    tipo: "shoe",
  },
  "tanShoe1.png": {
    tipo: "shoe",
  },
  "tanShoe2.png": {
    tipo: "shoe",
  },
  "tanShoe3.png": {
    tipo: "shoe",
  },
  "tanShoe4.png": {
    tipo: "shoe",
  },
  "tanShoe5.png": {
    tipo: "shoe",
  },
  "tint1_arm.png": {
    tipo: "arm",
  },
  "tint1_hand.png": {
    tipo: "hand",
  },
  "tint1_head.png": {
    tipo: "head",
  },
  "tint1_leg.png": {
    tipo: "Outros",
  },
  "tint1_neck.png": {
    tipo: "neck",
  },
  "tint2_arm.png": {
    tipo: "arm",
  },
  "tint2_hand.png": {
    tipo: "hand",
  },
  "tint2_head.png": {
    tipo: "head",
  },
  "tint2_leg.png": {
    tipo: "Outros",
  },
  "tint2_neck.png": {
    tipo: "neck",
  },
  "tint3_arm.png": {
    tipo: "arm",
  },
  "tint3_hand.png": {
    tipo: "hand",
  },
  "tint3_head.png": {
    tipo: "head",
  },
  "tint3_leg.png": {
    tipo: "Outros",
  },
  "tint3_neck.png": {
    tipo: "neck",
  },
  "tint4_arm.png": {
    tipo: "arm",
  },
  "tint4_hand.png": {
    tipo: "hand",
  },
  "tint4_head.png": {
    tipo: "head",
  },
  "tint4_leg.png": {
    tipo: "Outros",
  },
  "tint4_neck.png": {
    tipo: "neck",
  },
  "tint5_arm.png": {
    tipo: "arm",
  },
  "tint5_hand.png": {
    tipo: "hand",
  },
  "tint5_head.png": {
    tipo: "head",
  },
  "tint5_leg.png": {
    tipo: "Outros",
  },
  "tint5_neck.png": {
    tipo: "neck",
  },
  "tint6_arm.png": {
    tipo: "arm",
  },
  "tint6_hand.png": {
    tipo: "hand",
  },
  "tint6_head.png": {
    tipo: "head",
  },
  "tint6_leg.png": {
    tipo: "Outros",
  },
  "tint6_neck.png": {
    tipo: "neck",
  },
  "tint7_arm.png": {
    tipo: "arm",
  },
  "tint7_hand.png": {
    tipo: "hand",
  },
  "tint7_head.png": {
    tipo: "head",
  },
  "tint7_leg.png": {
    tipo: "Outros",
  },
  "tint7_neck.png": {
    tipo: "neck",
  },
  "tint8_arm.png": {
    tipo: "arm",
  },
  "tint8_hand.png": {
    tipo: "hand",
  },
  "tint8_head.png": {
    tipo: "head",
  },
  "tint8_leg.png": {
    tipo: "Outros",
  },
  "tint8_neck.png": {
    tipo: "neck",
  },
}
